taskingai/__init__.py
taskingai/_version.py
taskingai/config.py
taskingai/exceptions.py
taskingai/models.py
taskingai/assistant/__init__.py
taskingai/assistant/assistant.py
taskingai/assistant/chat.py
taskingai/assistant/memory.py
taskingai/assistant/message.py
taskingai/client/__init__.py
taskingai/client/api_client.py
taskingai/client/configuration.py
taskingai/client/constants.py
taskingai/client/error_handling.py
taskingai/client/exceptions.py
taskingai/client/rest.py
taskingai/client/stream.py
taskingai/client/utils.py
taskingai/client/apis/__init__.py
taskingai/client/apis/api_chat_completion.py
taskingai/client/apis/api_clean_chat_context.py
taskingai/client/apis/api_create_assistant.py
taskingai/client/apis/api_create_chat.py
taskingai/client/apis/api_create_collection.py
taskingai/client/apis/api_create_message.py
taskingai/client/apis/api_create_record.py
taskingai/client/apis/api_delete_assistant.py
taskingai/client/apis/api_delete_chat.py
taskingai/client/apis/api_delete_collection.py
taskingai/client/apis/api_delete_message.py
taskingai/client/apis/api_delete_record.py
taskingai/client/apis/api_generate_message.py
taskingai/client/apis/api_get_assistant.py
taskingai/client/apis/api_get_chat.py
taskingai/client/apis/api_get_collection.py
taskingai/client/apis/api_get_message.py
taskingai/client/apis/api_get_record.py
taskingai/client/apis/api_list_assistants.py
taskingai/client/apis/api_list_chats.py
taskingai/client/apis/api_list_collections.py
taskingai/client/apis/api_list_messages.py
taskingai/client/apis/api_list_records.py
taskingai/client/apis/api_query_collection_chunks.py
taskingai/client/apis/api_text_embedding.py
taskingai/client/apis/api_update_assistant.py
taskingai/client/apis/api_update_chat.py
taskingai/client/apis/api_update_collection.py
taskingai/client/apis/api_update_message.py
taskingai/client/apis/api_update_record.py
taskingai/client/models/__init__.py
taskingai/client/models/entities/__init__.py
taskingai-0.3.0.dist-info/METADATA
taskingai-0.3.0.dist-info/WHEEL
taskingai-0.3.0.dist-info/top_level.txt
taskingai-0.3.0.dist-info/RECORD
