Metadata-Version: 2.1
Name: taskingai
Version: 0.3.0
Summary: TaskingAI
Home-page: https://www.tasking.ai
Author-email: support@tasking.ai
Keywords: TaskingAI,LLM,AI
Requires-Dist: certifi>=14.05.14
Requires-Dist: six>=1.10
Requires-Dist: python-dateutil>=2.5.3
Requires-Dist: setuptools>=21.0.0
Requires-Dist: httpx>=0.23.0
Requires-Dist: pydantic>=2.5.0
